aws_lambda_deploy-1.0.0.dist-info/DESCRIPTION.rst
aws_lambda_deploy-1.0.0.dist-info/METADATA
aws_lambda_deploy-1.0.0.dist-info/RECORD
aws_lambda_deploy-1.0.0.dist-info/WHEEL
aws_lambda_deploy-1.0.0.dist-info/entry_points.txt
aws_lambda_deploy-1.0.0.dist-info/metadata.json
aws_lambda_deploy-1.0.0.dist-info/top_level.txt
lambda_deploy/__init__.py
lambda_deploy/decorators.py
lambda_deploy/extractors/__init__.py
lambda_deploy/extractors/base.py
lambda_deploy/extractors/decorator_extractor.py
lambda_deploy/extractors/regex_extractor.py
